Metadata-Version: 1.2
Name: fpga
Version: 0.0.2
Summary: APIs for FPGAs
Home-page: https://github.com/fpgaco/fpga
Author: Kenso Trabing
Author-email: ktrabing@acm.org
Maintainer: Kenso Trabing
Maintainer-email: ktrabing@acm.org
License:                                  Apache License
